custom_admin/__init__.py
custom_admin/api/__init__.py
custom_admin/api/action_functions.py
custom_admin/api/backends.py
custom_admin/api/inline_relation.py
custom_admin/api/permissions.py
custom_admin/api/urls.py
custom_admin/api/viewset_info.py
custom_admin/api/actions/__init__.py
custom_admin/api/actions/action_result.py
custom_admin/api/actions/admin_export.py
custom_admin/api/actions/admin_import.py
custom_admin/api/actions/delete_action.py
custom_admin/api/actions/export_csv_action.py
custom_admin/api/actions/view_actions_mixin.py
custom_admin/api/fields/__init__.py
custom_admin/api/fields/base.py
custom_admin/api/fields/char.py
custom_admin/api/fields/choice.py
custom_admin/api/fields/files.py
custom_admin/api/fields/int.py
custom_admin/api/fields/json.py
custom_admin/api/fields/numbers.py
custom_admin/api/fields/relation.py
custom_admin/api/filters/__init__.py
custom_admin/api/filters/base_admin_filter.py
custom_admin/api/filters/choices.py
custom_admin/api/filters/date_range.py
custom_admin/api/inlines/__init__.py
custom_admin/api/inlines/inline_graph.py
custom_admin/api/inlines/inline_table.py
custom_admin/api/inlines/inlines_type.py
custom_admin/api/inlines/interfaces.py
custom_admin/api/inlines/view_inline_mixin.py
custom_admin/api/serializers/__init__.py
custom_admin/api/serializers/auth_response.py
custom_admin/api/serializers/base_serializer.py
custom_admin/api/serializers/profile.py
custom_admin/api/tests/__init__.py
custom_admin/api/tests/test_filters.py
custom_admin/api/tests/test_scheme_get.py
custom_admin/api/tests/urls.py
custom_admin/api/views/__init__.py
custom_admin/api/views/autocomplete.py
custom_admin/api/views/base_admin_viewset.py
custom_admin/api/views/get_sections.py
custom_admin/api/views/token_auth.py
custom_admin/api/views/defaults/__init__.py
custom_admin/api/views/defaults/admin_log.py
custom_admin/api/views/defaults/groups.py
custom_admin/api/views/defaults/permissions.py
custom_admin/controllers/__init__.py
django_customvueadmin-0.2.87.dist-info/LICENSE
django_customvueadmin-0.2.87.dist-info/METADATA
django_customvueadmin-0.2.87.dist-info/WHEEL
django_customvueadmin-0.2.87.dist-info/top_level.txt
django_customvueadmin-0.2.87.dist-info/RECORD
