Metadata-Version: 2.1
Name: django-customvueadmin
Version: 0.2.87
Summary: A custom admin interface on Vue 3 and Vuetify with DRF backend that tries to Keep It Simple.
Home-page: https://innova-group-llc.github.io/custom_admin_docs/
License: BSD-3-Clause
Project-URL: Documentation, https://innova-group-llc.github.io/custom_admin_docs/
Project-URL: Source, https://github.com/Innova-Group-LLC/custom_admin
Classifier: Programming Language :: Python :: 3
Classifier: Programming Language :: Python :: 3 :: Only
Classifier: Programming Language :: Python :: 3.8
Classifier: Programming Language :: Python :: 3.9
Classifier: Programming Language :: Python :: 3.10
Classifier: Programming Language :: Python :: 3.11
Classifier: Programming Language :: Python :: 3.12
Requires-Python: >=3.8
License-File: LICENSE
